sfq/__init__.py
sfq/auth.py
sfq/ci_headers.py
sfq/crud.py
sfq/debug_cleanup.py
sfq/exceptions.py
sfq/http_client.py
sfq/mdapi.py
sfq/platform_events.py
sfq/py.typed
sfq/query.py
sfq/soap.py
sfq/telemetry.py
sfq/timeout_detector.py
sfq/utils.py
sfq-0.0.56.dist-info/METADATA
sfq-0.0.56.dist-info/WHEEL
sfq-0.0.56.dist-info/RECORD
