Metadata-Version: 2.4
Name: sfq
Version: 0.0.56
Summary: Python wrapper for the Salesforce's Query API.
Author-email: David Moruzzi <sfq.pypi@dmoruzi.com>
Keywords: salesforce,salesforce query
Classifier: Development Status :: 3 - Alpha
Classifier: Intended Audience :: Developers
Classifier: Programming Language :: Python :: 3.9
Classifier: Programming Language :: Python :: 3.10
Classifier: Programming Language :: Python :: 3.12
Classifier: Programming Language :: Python :: 3.13
Classifier: Topic :: Software Development :: Libraries :: Python Modules
Requires-Python: >=3.9
